{
  "string": [
    {
      "name": "entry_desc",
      "value": "description"
    },
    {
      "name": "MainAbility_desc",
      "value": "description"
    },
    {
      "name": "DataShareExtAbility_desc",
      "value": "description"
    },
    {
      "name": "RingtoneBackupExtAbility_desc",
      "value": "description"
    },
    {
      "name": "permission_read_audio",
      "value": "Allows access to the audio files in a user directory."
    },
    {
      "name": "permission_access_ringtone_resource",
      "value": "Allows access to the ringtone files in a user directory."
    },
    {
      "name": "permission_file_access_manager",
      "value": "Allows app read write files in file manager app."
    }
  ]
}
